eesdr_owrx_connector/connector.py
eesdr_owrx_connector-0.0.2.dist-info/LICENSE
eesdr_owrx_connector-0.0.2.dist-info/METADATA
eesdr_owrx_connector-0.0.2.dist-info/WHEEL
eesdr_owrx_connector-0.0.2.dist-info/entry_points.txt
eesdr_owrx_connector-0.0.2.dist-info/top_level.txt
eesdr_owrx_connector-0.0.2.dist-info/RECORD
