Metadata-Version: 2.1
Name: eesdr-owrx-connector
Version: 0.0.2
Summary: Connector to use the Expert Electronics TCI protocol to feed an OpenWebRX instance.
Author-email: "Matthew R. McDougal" <ka0s@arrl.net>
Project-URL: Homepage, https://github.com/ars-ka0s/eesdr-owrx-connector
Project-URL: Bug Tracker, https://github.com/ars-ka0s/eesdr-owrx-connector/issues
Classifier: Programming Language :: Python :: 3
Classifier: Development Status :: 3 - Alpha
Classifier: Framework :: AsyncIO
Classifier: Intended Audience :: Developers
Classifier: License :: OSI Approved :: BSD License
Classifier: Operating System :: OS Independent
Classifier: Topic :: Communications :: Ham Radio
Requires-Python: >=3.8
License-File: LICENSE
Requires-Dist: eesdr-tci >=0.1
